lonny_common_pg_queue/__init__.py
lonny_common_pg_queue/cfg.py
lonny_common_pg_queue/logger.py
lonny_common_pg_queue/queue.py
lonny_common_pg_queue-0.1.1.dist-info/LICENSE
lonny_common_pg_queue-0.1.1.dist-info/WHEEL
lonny_common_pg_queue-0.1.1.dist-info/METADATA
lonny_common_pg_queue-0.1.1.dist-info/RECORD
