Metadata-Version: 2.1
Name: lonny-common-pg-queue
Version: 0.1.1
Summary: A lightweight distributed queue using a postgres DB.
Home-page: https://lonny.io
Author: tlonny
Author-email: t@lonny.io
Requires-Python: >=3.8,<4.0
Classifier: Programming Language :: Python :: 3
Classifier: Programming Language :: Python :: 3.8
Project-URL: Repository, https://gitlab.com/lonny-common/pg-queue
